{
  "$name": "Component Tokens",
  "icon": {
    "unfilled": {
      "default": {
        "$scopes": [
          "ALL_SCOPES"
        ],
        "$type": "color",
        "$libraryName": "",
        "$collectionName": "semanticTokens",
        "$value": "{background.passive.neutral.subtle}"
      },
      "hover": {
        "$scopes": [
          "ALL_SCOPES"
        ],
        "$type": "color",
        "$libraryName": "",
        "$collectionName": "semanticTokens",
        "$value": "{background.active.neutral.hover}"
      },
      "disabled": {
        "$scopes": [
          "ALL_SCOPES"
        ],
        "$type": "color",
        "$libraryName": "",
        "$collectionName": "semanticTokens",
        "$value": "{background.active.neutral.disabled}"
      }
    },
    "filled": {
      "default": {
        "$scopes": [
          "ALL_SCOPES"
        ],
        "$type": "color",
        "$libraryName": "",
        "$collectionName": "semanticTokens",
        "$value": "{rating}"
      },
      "hover": {
        "$scopes": [
          "ALL_SCOPES"
        ],
        "$type": "color",
        "$libraryName": "",
        "$collectionName": "semanticTokens",
        "$value": "{rating}"
      },
      "active": {
        "$scopes": [
          "ALL_SCOPES"
        ],
        "$type": "color",
        "$libraryName": "",
        "$collectionName": "semanticTokens",
        "$value": "{rating}"
      },
      "disabled": {
        "$scopes": [
          "ALL_SCOPES"
        ],
        "$type": "color",
        "$libraryName": "",
        "$collectionName": "semanticTokens",
        "$value": "{background.active.neutral.disabled}"
      }
    }
  },
  "size": {
    "sm": {
      "$scopes": [
        "ALL_SCOPES"
      ],
      "$type": "dimension",
      "$libraryName": "",
      "$collectionName": "semanticTokens",
      "$value": "{icon.sm}"
    },
    "md": {
      "$scopes": [
        "ALL_SCOPES"
      ],
      "$type": "dimension",
      "$libraryName": "",
      "$collectionName": "semanticTokens",
      "$value": "{icon.md}"
    },
    "lg": {
      "$scopes": [
        "ALL_SCOPES"
      ],
      "$type": "dimension",
      "$libraryName": "",
      "$collectionName": "semanticTokens",
      "$value": "{icon.lg}"
    }
  },
  "gap": {
    "sm": {
      "$scopes": [
        "ALL_SCOPES"
      ],
      "$type": "spacing",
      "$libraryName": "",
      "$collectionName": "semanticTokens",
      "$value": "{gap.xxs}"
    },
    "md": {
      "$scopes": [
        "ALL_SCOPES"
      ],
      "$type": "spacing",
      "$libraryName": "",
      "$collectionName": "semanticTokens",
      "$value": "{gap.xs}"
    },
    "lg": {
      "$scopes": [
        "ALL_SCOPES"
      ],
      "$type": "spacing",
      "$libraryName": "",
      "$collectionName": "semanticTokens",
      "$value": "{gap.s}"
    },
    "mobile": {
      "$scopes": [
        "ALL_SCOPES"
      ],
      "$libraryName": "",
      "$type": "spacing",
      "$value": "{padding.s}",
      "$collectionName": "semanticTokens"
    }
  },
  "color": {
    "$scopes": [
      "ALL_SCOPES"
    ],
    "$libraryName": "",
    "$type": "color",
    "$value": "{background.passive.neutral.default}",
    "$collectionName": "semanticTokens"
  },
  "count": {
    "color": {
      "$scopes": [
        "ALL_SCOPES"
      ],
      "$libraryName": "",
      "$type": "color",
      "$value": "{background.passive.neutral.default}",
      "$collectionName": "semanticTokens"
    }
  },
  "font": {
    "size": {
      "mobile": {
        "$scopes": [
          "ALL_SCOPES"
        ],
        "$libraryName": "",
        "$type": "fontSizes",
        "$value": "{typography.fontSize.3}",
        "$collectionName": "primitives"
      }
    }
  },
  "star": {
    "color": {
      "empty": {
        "$scopes": [
          "ALL_SCOPES"
        ],
        "$libraryName": "",
        "$type": "color",
        "$value": "{background.passive.neutral.default}",
        "$collectionName": "semanticTokens"
      },
      "filled": {
        "$scopes": [
          "ALL_SCOPES"
        ],
        "$libraryName": "",
        "$type": "color",
        "$value": "{background.passive.neutral.default}",
        "$collectionName": "semanticTokens"
      }
    },
    "gap": {
      "$scopes": [
        "ALL_SCOPES"
      ],
      "$libraryName": "",
      "$type": "spacing",
      "$value": "{padding.s}",
      "$collectionName": "semanticTokens"
    }
  },
  "text": {
    "color": {
      "$scopes": [
        "ALL_SCOPES"
      ],
      "$libraryName": "",
      "$type": "color",
      "$value": "{background.passive.neutral.default}",
      "$collectionName": "semanticTokens"
    },
    "font": {
      "size": {
        "$scopes": [
          "ALL_SCOPES"
        ],
        "$libraryName": "",
        "$type": "fontSizes",
        "$value": "{typography.fontSize.3}",
        "$collectionName": "primitives"
      }
    },
    "line": {
      "height": {
        "$scopes": [
          "ALL_SCOPES"
        ],
        "$libraryName": "",
        "$type": "lineHeights",
        "$value": "{typography.lineHeight.16}",
        "$collectionName": "primitives"
      }
    }
  }
}