{
  "modes": {
    "Reservio": {
      "icon-size-1": {
        "$scopes": [
          "ALL_SCOPES"
        ],
        "$hiddenFromPublishing": true,
        "$type": "dimension",
        "$value": 16
      },
      "icon-size-2": {
        "$scopes": [
          "ALL_SCOPES"
        ],
        "$hiddenFromPublishing": true,
        "$type": "dimension",
        "$value": 20
      },
      "icon-size-3": {
        "$scopes": [
          "ALL_SCOPES"
        ],
        "$hiddenFromPublishing": true,
        "$type": "dimension",
        "$value": 24
      },
      "icon-size-4": {
        "$scopes": [
          "ALL_SCOPES"
        ],
        "$hiddenFromPublishing": true,
        "$type": "dimension",
        "$value": 32
      },
      "icon-size-5": {
        "$scopes": [
          "ALL_SCOPES"
        ],
        "$hiddenFromPublishing": true,
        "$type": "dimension",
        "$value": 40
      },
      "icon-size-6": {
        "$scopes": [
          "ALL_SCOPES"
        ],
        "$hiddenFromPublishing": true,
        "$type": "dimension",
        "$value": 48
      },
      "icon-size-7": {
        "$scopes": [
          "ALL_SCOPES"
        ],
        "$hiddenFromPublishing": true,
        "$type": "dimension",
        "$value": 56
      },
      "icon-size-8": {
        "$scopes": [
          "ALL_SCOPES"
        ],
        "$hiddenFromPublishing": true,
        "$type": "dimension",
        "$value": 64
      }
    },
    "Survio": {
      "icon-size-1": {
        "$scopes": [
          "ALL_SCOPES"
        ],
        "$hiddenFromPublishing": true,
        "$type": "dimension",
        "$value": 16
      },
      "icon-size-2": {
        "$scopes": [
          "ALL_SCOPES"
        ],
        "$hiddenFromPublishing": true,
        "$type": "dimension",
        "$value": 20
      },
      "icon-size-3": {
        "$scopes": [
          "ALL_SCOPES"
        ],
        "$hiddenFromPublishing": true,
        "$type": "dimension",
        "$value": 24
      },
      "icon-size-4": {
        "$scopes": [
          "ALL_SCOPES"
        ],
        "$hiddenFromPublishing": true,
        "$type": "dimension",
        "$value": 32
      },
      "icon-size-5": {
        "$scopes": [
          "ALL_SCOPES"
        ],
        "$hiddenFromPublishing": true,
        "$type": "dimension",
        "$value": 40
      },
      "icon-size-6": {
        "$scopes": [
          "ALL_SCOPES"
        ],
        "$hiddenFromPublishing": true,
        "$type": "dimension",
        "$value": 48
      },
      "icon-size-7": {
        "$scopes": [
          "ALL_SCOPES"
        ],
        "$hiddenFromPublishing": true,
        "$type": "dimension",
        "$value": 56
      },
      "icon-size-8": {
        "$scopes": [
          "ALL_SCOPES"
        ],
        "$hiddenFromPublishing": true,
        "$type": "dimension",
        "$value": 64
      }
    }
  },
  "$name": "Icon Size"
}